odoo/addons/hr_leave_custom_hour_interval/README.rst
odoo/addons/hr_leave_custom_hour_interval/__init__.py
odoo/addons/hr_leave_custom_hour_interval/__manifest__.py
odoo/addons/hr_leave_custom_hour_interval/i18n/es.po
odoo/addons/hr_leave_custom_hour_interval/i18n/hr_leave_custom_hour_interval.pot
odoo/addons/hr_leave_custom_hour_interval/i18n/hr_leave_hour.pot
odoo/addons/hr_leave_custom_hour_interval/i18n/it.po
odoo/addons/hr_leave_custom_hour_interval/models/__init__.py
odoo/addons/hr_leave_custom_hour_interval/models/hr_leave.py
odoo/addons/hr_leave_custom_hour_interval/readme/CONTRIBUTORS.rst
odoo/addons/hr_leave_custom_hour_interval/readme/DESCRIPTION.rst
odoo/addons/hr_leave_custom_hour_interval/readme/USAGE.rst
odoo/addons/hr_leave_custom_hour_interval/static/description/icon.png
odoo/addons/hr_leave_custom_hour_interval/static/description/index.html
odoo/addons/hr_leave_custom_hour_interval/views/hr_leave.xml
odoo14_addon_hr_leave_custom_hour_interval-14.0.1.0.1.dev8.dist-info/METADATA
odoo14_addon_hr_leave_custom_hour_interval-14.0.1.0.1.dev8.dist-info/WHEEL
odoo14_addon_hr_leave_custom_hour_interval-14.0.1.0.1.dev8.dist-info/top_level.txt
odoo14_addon_hr_leave_custom_hour_interval-14.0.1.0.1.dev8.dist-info/RECORD
